langchain_google_vertexai/__init__.py
langchain_google_vertexai/_anthropic_parsers.py
langchain_google_vertexai/_anthropic_utils.py
langchain_google_vertexai/_base.py
langchain_google_vertexai/_client_utils.py
langchain_google_vertexai/_compat.py
langchain_google_vertexai/_enums.py
langchain_google_vertexai/_image_utils.py
langchain_google_vertexai/_retry.py
langchain_google_vertexai/_utils.py
langchain_google_vertexai/callbacks.py
langchain_google_vertexai/chains.py
langchain_google_vertexai/chat_models.py
langchain_google_vertexai/embeddings.py
langchain_google_vertexai/functions_utils.py
langchain_google_vertexai/llms.py
langchain_google_vertexai/model_garden.py
langchain_google_vertexai/py.typed
langchain_google_vertexai/utils.py
langchain_google_vertexai/vision_models.py
langchain_google_vertexai/data/__init__.py
langchain_google_vertexai/data/_profiles.py
langchain_google_vertexai/data/profile_augmentations.toml
langchain_google_vertexai/evaluators/__init__.py
langchain_google_vertexai/evaluators/_core.py
langchain_google_vertexai/evaluators/evaluation.py
langchain_google_vertexai/model_garden_maas/__init__.py
langchain_google_vertexai/model_garden_maas/_base.py
langchain_google_vertexai/model_garden_maas/llama.py
langchain_google_vertexai/model_garden_maas/mistral.py
langchain_google_vertexai/vectorstores/__init__.py
langchain_google_vertexai/vectorstores/_sdk_manager.py
langchain_google_vertexai/vectorstores/_searcher.py
langchain_google_vertexai/vectorstores/_utils.py
langchain_google_vertexai/vectorstores/document_storage.py
langchain_google_vertexai/vectorstores/vectorstores.py
langchain_google_vertexai-3.2.1.dist-info/METADATA
langchain_google_vertexai-3.2.1.dist-info/WHEEL
langchain_google_vertexai-3.2.1.dist-info/licenses/LICENSE
langchain_google_vertexai-3.2.1.dist-info/RECORD
