Metadata-Version: 2.4
Name: langchain-google-vertexai
Version: 3.2.1
Summary: An integration package connecting Google VertexAI and LangChain
Project-URL: Homepage, https://docs.langchain.com/oss/python/integrations/providers/google
Project-URL: Documentation, https://reference.langchain.com/python/integrations/langchain_google_vertexai/
Project-URL: Source, https://github.com/langchain-ai/langchain-google/tree/master/libs/vertexai
Project-URL: Changelog, https://github.com/langchain-ai/langchain-google/releases?q=%22vertexai%22
Project-URL: Twitter, https://x.com/LangChainAI
Project-URL: Slack, https://www.langchain.com/join-community
Project-URL: Reddit, https://www.reddit.com/r/LangChain/
License: MIT
License-File: LICENSE
Requires-Python: <4.0.0,>=3.10.0
Requires-Dist: bottleneck<2.0.0,>=1.4.0
Requires-Dist: google-cloud-aiplatform<2.0.0,>=1.97.0
Requires-Dist: google-cloud-storage<4.0.0,>=2.18.0
Requires-Dist: httpx-sse<1.0.0,>=0.4.0
Requires-Dist: httpx<1.0.0,>=0.28.0
Requires-Dist: langchain-core<2.0.0,>=1.2.5
Requires-Dist: numexpr<3.0.0,>=2.8.6
Requires-Dist: pyarrow<23.0.0,>=19.0.1
Requires-Dist: pydantic<3.0.0,>=2.9.0
Requires-Dist: validators<1.0.0,>=0.22.0
Provides-Extra: anthropic
Requires-Dist: anthropic<1.0.0,>=0.35.0; extra == 'anthropic'
Provides-Extra: mistral
Requires-Dist: langchain-mistralai<2.0.0,>=0.2.0; extra == 'mistral'
